sync_or_swim/__init__.py
sync_or_swim/__main__.py
sync_or_swim/py.typed
sync_or_swim-0.1.0.dist-info/METADATA
sync_or_swim-0.1.0.dist-info/WHEEL
sync_or_swim-0.1.0.dist-info/entry_points.txt
sync_or_swim-0.1.0.dist-info/top_level.txt
sync_or_swim-0.1.0.dist-info/RECORD
