Metadata-Version: 2.1
Name: sync-or-swim
Version: 0.1.0
Summary: Sync your data files across all of your machines (tinyurl.com/sync-or-swim)
Home-page: https://github.com/bbugyi200/sync-or-swim
Author: Bryan M Bugyi
Author-email: bryanbugyi34@gmail.com
License: MIT license
Classifier: Development Status :: 3 - Alpha
Classifier: Intended Audience :: Developers
Classifier: License :: OSI Approved :: MIT License
Classifier: Natural Language :: English
Classifier: Programming Language :: Python :: 3
Classifier: Programming Language :: Python :: 3.8
Classifier: Programming Language :: Python :: 3.9
Classifier: Programming Language :: Python :: 3.10
Requires-Python: >=3.8
Requires-Dist: bolton-clack (~=0.3.1)
Requires-Dist: bolton-logrus (~=0.1.0)
